pytee2/__about__.py
pytee2/__init__.py
pytee2-0.0.1.dist-info/METADATA
pytee2-0.0.1.dist-info/WHEEL
pytee2-0.0.1.dist-info/licenses/LICENSE
pytee2-0.0.1.dist-info/RECORD
