Metadata-Version: 2.1
Name: pytee2
Version: 0.0.1
Summary: redirecting streams within Python scripts
Project-URL: Documentation, https://github.com/laf070810/pytee2#readme
Project-URL: Issues, https://github.com/laf070810/pytee2/issues
Project-URL: Source, https://github.com/laf070810/pytee2
Author-email: Anfeng Li <laf070810@163.com>
License-Expression: MIT
License-File: LICENSE
Classifier: Development Status :: 4 - Beta
Classifier: Programming Language :: Python
Classifier: Programming Language :: Python :: 3.8
Classifier: Programming Language :: Python :: 3.9
Classifier: Programming Language :: Python :: 3.10
Classifier: Programming Language :: Python :: 3.11
Classifier: Programming Language :: Python :: 3.12
Classifier: Programming Language :: Python :: Implementation :: CPython
Classifier: Programming Language :: Python :: Implementation :: PyPy
Requires-Python: >=3.8
